__init__.py
htmllabel.py
json2markdown.py
parser.py
HtmlPageParser-0.0.4.dist-info/LICENSE
HtmlPageParser-0.0.4.dist-info/METADATA
HtmlPageParser-0.0.4.dist-info/WHEEL
HtmlPageParser-0.0.4.dist-info/top_level.txt
HtmlPageParser-0.0.4.dist-info/RECORD
