Metadata-Version: 2.1
Name: HtmlPageParser
Version: 0.0.4
Summary: A generic HTML page parser
Author-email: snjyor <snjyor@163.com>
Project-URL: Homepage, https://github.com/snjyor/HtmlPageParser
Classifier: Programming Language :: Python :: 3
Classifier: License :: OSI Approved :: MIT License
Classifier: Operating System :: OS Independent
Requires-Python: >=3.7
License-File: LICENSE
